{
  "areaId": 4,
  "areaZipCode": 105,
  "cityId": 1,
  "clickforceVastUrl": "https://vast.holmesmind.com/adserver/vast.xml?z=13347&vsize=lager&d=6&city=TPE",
  "headquarterId": 466,
  "hivestackVastUrl": "https://apps.hivestack.com/nirvana/api/v1/units/schedulevast/6425?apikey=$2b$12$yTXHKIUP7E8iLQ0ytr6B0e:2770c2ae-dcde-4728-85f8-1b4b7ffcc763",
  "id": 6425,
  "innerAdFrequency": 1800,
  "innerBannerFrequency": 30,
  "isClickforceVastOn": false,
  "isEnablePlayInnerAd": false,
  "isEnablePlayInnerBanner": false,
  "isFaceRecognitionOn": false,
  "isHivestackVastOn": false,
  "isPowerSavingOn": false,
  "isQuickCut": false,
  "isScalpDetectionOn": true,
  "isStylistOn": true,
  "isYahooVastOn": false,
  "latestLauncherVersion": "",
  "latestMirrorVersion": "",
  "latestTestLauncherVersion": "",
  "latestTestMirrorVersion": "",
  "lowestAdsAmount": 15,
  "name": "Star 小魔鏡",
  "periods": [],
  "programLength": 150,
  "sn": "SMR000275",
  "storeId": 1306,
  "storeName": "star測試定時開關機",
  "tabs": [],
  "testMode": false,
  "vastRequestedFrequency": 3,
  "vastUrl": "",
  "vendor": "asus",
  "version": -1,
  "yahooVastUrl": "https://web.ssp.yahoo.com/admax/adServe.do?dcn=8a9699740180801dbeea21336e4900a2&pos=solmate_tw_salon_north_video_1920x1080&secure=1&d(id24)=SMR000275&im=1&ip=:ip_address&ua=:user_agent"
}